ez_pyload/__init__.py
ez_pyload/__main__.py
ez_pyload/download.py
ez_pyload/patches.py
ez_pyload-1.0.4.dist-info/METADATA
ez_pyload-1.0.4.dist-info/WHEEL
ez_pyload-1.0.4.dist-info/entry_points.txt
ez_pyload-1.0.4.dist-info/RECORD
