Metadata-Version: 2.1
Name: ez-pyload
Version: 1.0.4
Summary: Wrapper for pyLoad to allow downloading files through Python (no webserver). Includes CLI
License: MIT
Author: 7x11x13
Author-email: x7x11x13@gmail.com
Requires-Python: >=3.6,<4.0
Classifier: License :: OSI Approved :: MIT License
Classifier: Programming Language :: Python :: 3
Classifier: Programming Language :: Python :: 3.6
Classifier: Programming Language :: Python :: 3.7
Classifier: Programming Language :: Python :: 3.8
Classifier: Programming Language :: Python :: 3.9
Classifier: Programming Language :: Python :: 3.10
Classifier: Programming Language :: Python :: 3.11
Classifier: Programming Language :: Python :: 3.12
Requires-Dist: pyload-ng (>=0.5.0b3.dev81,<0.6.0)
